[
{
"urtea":2019,
"hilea":9,
"bertsioa":0,
"eguna":4,
"sarrera":"Purea",
"nagusia":"Solomoa",
"postrea":"Jogurta"
},
{
"urtea":2019,
"hilea":9,
"bertsioa":0,
"eguna":5,
"sarrera":"Makarroiak",
"nagusia":"Tortilla",
"postrea":"Jogurta"
},
{
"urtea":2019,
"hilea":9,
"bertsioa":0,
"eguna":6,
"sarrera":"Patatak Ilarrekin",
"nagusia":"Legatza",
"postrea":"Jogurta"
},
{
"urtea":2019,
"hilea":9,
"bertsioa":0,
"eguna":9,
"sarrera":"Dilistak arroz integralarekin",
"nagusia":"Patata tortilla saltsa tomatearekin",
"postrea":"Fruta"
},
{
"urtea":2019,
"hilea":9,
"bertsioa":0,
"eguna":10,
"sarrera":"Barazki purea",
"nagusia":"Legatz xerra erromako erara mahonesarekin",
"postrea":"Jogurta edo fruta"
},
{
"urtea":2019,
"hilea":9,
"bertsioa":0,
"eguna":11,
"sarrera":"Indaba gorriak",
"nagusia":"Kroketak patata frijituekin",
"postrea":"Fruta"
},
{
"urtea":2019,
"hilea":9,
"bertsioa":0,
"eguna":12,
"sarrera":"Barazki paella",
"nagusia":"Oilasko izter errea urazarekin",
"postrea":"Fruta"
},
{
"urtea":2019,
"hilea":9,
"bertsioa":0,
"eguna":13,
"sarrera":"Lekak patatekin",
"nagusia":"Txahal xerra piper gorriekin",
"postrea":"Fruta"
},
{
"urtea":2019,
"hilea":9,
"bertsioa":0,
"eguna":16,
"sarrera":"JAIA",
"nagusia":"JAIA",
"postrea":"JAIA"
},
{
"urtea":2019,
"hilea":9,
"bertsioa":0,
"eguna":17,
"sarrera":"Dilistak gaztelako erara",
"nagusia":"Landako tortilla tomate entsaladarekin",
"postrea":"Fruta"
},
{
"urtea":2019,
"hilea":9,
"bertsioa":0,
"eguna":18,
"sarrera":"Makarroiak tomatearekin",
"nagusia":"Oilasko xerra piper berdeekin",
"postrea":"Banillaszko natillak edo fruta"
},
{
"urtea":2019,
"hilea":9,
"bertsioa":0,
"eguna":19,
"sarrera":"Etxeko entsalada",
"nagusia":"Indaba zuriak",
"postrea":"Fruta"
},
{
"urtea":2019,
"hilea":9,
"bertsioa":0,
"eguna":20,
"sarrera":"Kalabazin Purea",
"nagusia":"Solomoa ragouta patata karratuekin",
"postrea":"Fruta"
},
{
"urtea":2019,
"hilea":9,
"bertsioa":0,
"eguna":23,
"sarrera":"Lekak patatekin",
"nagusia":"%100 txahal erra barazkitxoekin",
"postrea":"Fruta"
},
{
"urtea":2019,
"hilea":9,
"bertsioa":0,
"eguna":24,
"sarrera":"Arroza tomatearekin",
"nagusia":"Legatza erromako erara limoiarekin",
"postrea":"Jogurta edo fruta"
},
{
"urtea":2019,
"hilea":9,
"bertsioa":0,
"eguna":25,
"sarrera":"Txitxirioak",
"nagusia":"Arrautza egosiak piperradakin",
"postrea":"Fruta"
},
{
"urtea":2019,
"hilea":9,
"bertsioa":0,
"eguna":26,
"sarrera":"Hegazti eta eltzeko zopa izarrekin",
"nagusia":"Giarra tomate entsaladarekin",
"postrea":"Txokolate"
},
{
"urtea":2019,
"hilea":9,
"bertsioa":0,
"eguna":27,
"sarrera":"Patatak errioxa erara",
"nagusia":"Atunezko enpanadillak urazarekin",
"postrea":"Fruta"
},
{
"urtea":2019,
"hilea":9,
"bertsioa":0,
"eguna":30,
"sarrera":"Arrain zopa",
"nagusia":"Albondigak saltsan txanpiekin",
"postrea":"Fruta"
}
]
